plezmo/__init__.py
plezmo/connectivity.py
plezmo/plezmo_api.py
plezmo/elements/__init__.py
plezmo/elements/element_factory.py
plezmo/elements/element_types.py
plezmo/elements/plezmo_color.py
plezmo/elements/plezmo_display.py
plezmo/elements/plezmo_distance.py
plezmo/elements/plezmo_element.py
plezmo/elements/plezmo_light.py
plezmo/elements/plezmo_motion.py
plezmo/elements/plezmo_motor.py
plezmo/elements/plezmo_music.py
plezmo/events/__init__.py
plezmo/events/event_dispatcher.py
plezmo/plezmo_exceptions/__init__.py
plezmo/plezmo_exceptions/exceptions.py
plezmo/utils/__init__.py
plezmo/utils/color.py
plezmo/utils/command_helper.py
plezmo/utils/constants.py
plezmo/utils/logger.py
plezmo/utils/msg_helper.py
plezmo/utils/serial_ports.py
plezmo-1.0.3.dist-info/LICENSE.txt
plezmo-1.0.3.dist-info/METADATA
plezmo-1.0.3.dist-info/WHEEL
plezmo-1.0.3.dist-info/top_level.txt
plezmo-1.0.3.dist-info/RECORD
