Metadata-Version: 2.1
Name: plezmo
Version: 1.0.3
Summary: UNKNOWN
Home-page: https://github.com/plezmo/python-sdk-examples
Author: Gunakar Pvt Ltd
Author-email: support@gunakar.com
License: Modified BSD License
Platform: UNKNOWN
Classifier: Development Status :: 5 - Production/Stable
Classifier: Programming Language :: Python :: 3.7
Classifier: Operating System :: OS Independent
Requires-Python: >=3.7, !=3.0.*, !=3.1.*, !=3.2.*, !=3.3.*, !=3.4.*, !=3.5.*, !=3.6.*, <4
Requires-Dist: plezmo-ble-driver-py (>=0.12.1)
Requires-Dist: pyserial (<=3.4)
